iperflexer/iperfexpressions.py
iperflexer/finder.rst
iperflexer/unitconverter.py
iperflexer/main.rst
iperflexer/baseclass.rst
iperflexer/main.py
iperflexer/conf.py
iperflexer/oatbran.py
iperflexer/readme.rst
iperflexer/coroutine.rst
iperflexer/unitconverter.rst
iperflexer/iperfparser.rst
iperflexer/iperfparser.py
iperflexer/coroutine.py
iperflexer/sumparser.rst
iperflexer/iperfexpressions.rst
iperflexer/__init__.py
iperflexer/sumparser.py
iperflexer/baseclass.py
iperflexer/index.rst
iperflexer/argumentparser.rst
iperflexer/argumentparser.py
iperflexer/finder.py
iperflexer/infrastructure/index_builder.py
iperflexer/infrastructure/index_builder.rst
iperflexer/infrastructure/__init__.py
iperflexer/infrastructure/index.rst
iperflexer-0.1.4.dist-info/DESCRIPTION.rst
iperflexer-0.1.4.dist-info/WHEEL
iperflexer-0.1.4.dist-info/entry_points.txt
iperflexer-0.1.4.dist-info/metadata.json
iperflexer-0.1.4.dist-info/RECORD
iperflexer-0.1.4.dist-info/METADATA
iperflexer-0.1.4.dist-info/top_level.txt
