Metadata-Version: 2.0
Name: iperflexer
Version: 0.1.4
Summary: A program to parse iperf files
Home-page: https://bitbucket.org/cloisteredmonkey-admin/iperflexer
Author: russell
Author-email: necromuralist@gmail.com
License: MIT
Platform: linux
